[{"true_count": 0, "frame_count": 0, "frame_path": "tmp/frame_0.jpg", "predictions": [], "persons": 0}, {"true_count": 5, "frame_count": 1, "frame_path": "tmp/frame_1.jpg", "predictions": [], "persons": 0}, {"true_count": 10, "frame_count": 2, "frame_path": "tmp/frame_2.jpg", "predictions": [], "persons": 0}, {"true_count": 15, "frame_count": 3, "frame_path": "tmp/frame_3.jpg", "predictions": [], "persons": 0}, {"true_count": 20, "frame_count": 4, "frame_path": "tmp/frame_4.jpg", "predictions": [], "persons": 0}, {"true_count": 25, "frame_count": 5, "frame_path": "tmp/frame_5.jpg", "predictions": [], "persons": 0}, {"true_count": 30, "frame_count": 6, "frame_path": "tmp/frame_6.jpg", "predictions": [], "persons": 0}, {"true_count": 35, "frame_count": 7, "frame_path": "tmp/frame_7.jpg", "predictions": [], "persons": 0}, {"true_count": 40, "frame_count": 8, "frame_path": "tmp/frame_8.jpg", "predictions": [], "persons": 0}, {"true_count": 45, "frame_count": 9, "frame_path": "tmp/frame_9.jpg", "predictions": [{"confidence": 0.702292, "label": "person", "y_min": 1, "x_min": 201, "y_max": 95, "x_max": 264}], "persons": 1}, {"true_count": 50, "frame_count": 10, "frame_path": "tmp/frame_10.jpg", "predictions": [{"confidence": 0.5689891, "label": "person", "y_min": 2, "x_min": 192, "y_max": 106, "x_max": 270}], "persons": 1}, {"true_count": 55, "frame_count": 11, "frame_path": "tmp/frame_11.jpg", "predictions": [], "persons": 0}, {"true_count": 60, "frame_count": 12, "frame_path": "tmp/frame_12.jpg", "predictions": [], "persons": 0}, {"true_count": 65, "frame_count": 13, "frame_path": "tmp/frame_13.jpg", "predictions": [], "persons": 0}, {"true_count": 70, "frame_count": 14, "frame_path": "tmp/frame_14.jpg", "predictions": [], "persons": 0}, {"true_count": 75, "frame_count": 15, "frame_path": "tmp/frame_15.jpg", "predictions": [], "persons": 0}, {"true_count": 80, "frame_count": 16, "frame_path": "tmp/frame_16.jpg", "predictions": [{"confidence": 0.6306232, "label": "bird", "y_min": 81, "x_min": 225, "y_max": 206, "x_max": 299}], "persons": 0}, {"true_count": 85, "frame_count": 17, "frame_path": "tmp/frame_17.jpg", "predictions": [], "persons": 0}, {"true_count": 90, "frame_count": 18, "frame_path": "tmp/frame_18.jpg", "predictions": [], "persons": 0}, {"true_count": 95, "frame_count": 19, "frame_path": "tmp/frame_19.jpg", "predictions": [], "persons": 0}, {"true_count": 100, "frame_count": 20, "frame_path": "tmp/frame_20.jpg", "predictions": [{"confidence": 0.5176512, "label": "person", "y_min": 2, "x_min": 189, "y_max": 90, "x_max": 231}, {"confidence": 0.6474065, "label": "person", "y_min": 150, "x_min": 247, "y_max": 270, "x_max": 312}, {"confidence": 0.6739508, "label": "person", "y_min": 2, "x_min": 106, "y_max": 109, "x_max": 161}], "persons": 3}, {"true_count": 105, "frame_count": 21, "frame_path": "tmp/frame_21.jpg", "predictions": [{"confidence": 0.6805239, "label": "person", "y_min": 2, "x_min": 177, "y_max": 98, "x_max": 249}], "persons": 1}, {"true_count": 110, "frame_count": 22, "frame_path": "tmp/frame_22.jpg", "predictions": [], "persons": 0}, {"true_count": 115, "frame_count": 23, "frame_path": "tmp/frame_23.jpg", "predictions": [{"confidence": 0.5154907, "label": "horse", "y_min": 43, "x_min": 113, "y_max": 161, "x_max": 170}, {"confidence": 0.8002048, "label": "person", "y_min": 13, "x_min": 175, "y_max": 143, "x_max": 241}], "persons": 1}, {"true_count": 120, "frame_count": 24, "frame_path": "tmp/frame_24.jpg", "predictions": [{"confidence": 0.490604, "label": "person", "y_min": 63, "x_min": 115, "y_max": 185, "x_max": 168}, {"confidence": 0.7607029, "label": "person", "y_min": 34, "x_min": 182, "y_max": 156, "x_max": 247}], "persons": 2}, {"true_count": 125, "frame_count": 25, "frame_path": "tmp/frame_25.jpg", "predictions": [{"confidence": 0.71585447, "label": "horse", "y_min": 92, "x_min": 114, "y_max": 202, "x_max": 165}, {"confidence": 0.76905453, "label": "person", "y_min": 49, "x_min": 187, "y_max": 159, "x_max": 255}], "persons": 1}, {"true_count": 130, "frame_count": 26, "frame_path": "tmp/frame_26.jpg", "predictions": [{"confidence": 0.56344026, "label": "person", "y_min": 103, "x_min": 110, "y_max": 220, "x_max": 168}, {"confidence": 0.8230232, "label": "person", "y_min": 68, "x_min": 188, "y_max": 189, "x_max": 263}], "persons": 2}, {"true_count": 135, "frame_count": 27, "frame_path": "tmp/frame_27.jpg", "predictions": [{"confidence": 0.86710143, "label": "person", "y_min": 91, "x_min": 187, "y_max": 219, "x_max": 265}], "persons": 1}, {"true_count": 140, "frame_count": 28, "frame_path": "tmp/frame_28.jpg", "predictions": [{"confidence": 0.8125265, "label": "person", "y_min": 114, "x_min": 182, "y_max": 217, "x_max": 259}], "persons": 1}, {"true_count": 145, "frame_count": 29, "frame_path": "tmp/frame_29.jpg", "predictions": [], "persons": 0}, {"true_count": 150, "frame_count": 30, "frame_path": "tmp/frame_30.jpg", "predictions": [{"confidence": 0.620333, "label": "horse", "y_min": 153, "x_min": 183, "y_max": 278, "x_max": 252}, {"confidence": 0.7185293, "label": "person", "y_min": 188, "x_min": 122, "y_max": 297, "x_max": 179}], "persons": 1}, {"true_count": 155, "frame_count": 31, "frame_path": "tmp/frame_31.jpg", "predictions": [{"confidence": 0.61648864, "label": "person", "y_min": 176, "x_min": 190, "y_max": 284, "x_max": 257}], "persons": 1}, {"true_count": 160, "frame_count": 32, "frame_path": "tmp/frame_32.jpg", "predictions": [{"confidence": 0.45135844, "label": "person", "y_min": 195, "x_min": 192, "y_max": 287, "x_max": 266}, {"confidence": 0.51111346, "label": "person", "y_min": 232, "x_min": 120, "y_max": 298, "x_max": 181}], "persons": 2}, {"true_count": 165, "frame_count": 33, "frame_path": "tmp/frame_33.jpg", "predictions": [{"confidence": 0.76046544, "label": "person", "y_min": 216, "x_min": 190, "y_max": 298, "x_max": 272}], "persons": 1}, {"true_count": 170, "frame_count": 34, "frame_path": "tmp/frame_34.jpg", "predictions": [{"confidence": 0.8411283, "label": "person", "y_min": 238, "x_min": 190, "y_max": 299, "x_max": 270}], "persons": 1}, {"true_count": 175, "frame_count": 35, "frame_path": "tmp/frame_35.jpg", "predictions": [{"confidence": 0.6117752, "label": "person", "y_min": 256, "x_min": 192, "y_max": 300, "x_max": 265}], "persons": 1}, {"true_count": 180, "frame_count": 36, "frame_path": "tmp/frame_36.jpg", "predictions": [], "persons": 0}, {"true_count": 185, "frame_count": 37, "frame_path": "tmp/frame_37.jpg", "predictions": [], "persons": 0}, {"true_count": 190, "frame_count": 38, "frame_path": "tmp/frame_38.jpg", "predictions": [], "persons": 0}, {"true_count": 195, "frame_count": 39, "frame_path": "tmp/frame_39.jpg", "predictions": [], "persons": 0}, {"true_count": 200, "frame_count": 40, "frame_path": "tmp/frame_40.jpg", "predictions": [], "persons": 0}, {"true_count": 205, "frame_count": 41, "frame_path": "tmp/frame_41.jpg", "predictions": [], "persons": 0}, {"true_count": 210, "frame_count": 42, "frame_path": "tmp/frame_42.jpg", "predictions": [], "persons": 0}, {"true_count": 215, "frame_count": 43, "frame_path": "tmp/frame_43.jpg", "predictions": [], "persons": 0}, {"true_count": 220, "frame_count": 44, "frame_path": "tmp/frame_44.jpg", "predictions": [], "persons": 0}, {"true_count": 225, "frame_count": 45, "frame_path": "tmp/frame_45.jpg", "predictions": [], "persons": 0}, {"true_count": 230, "frame_count": 46, "frame_path": "tmp/frame_46.jpg", "predictions": [], "persons": 0}, {"true_count": 235, "frame_count": 47, "frame_path": "tmp/frame_47.jpg", "predictions": [], "persons": 0}, {"true_count": 240, "frame_count": 48, "frame_path": "tmp/frame_48.jpg", "predictions": [], "persons": 0}, {"true_count": 245, "frame_count": 49, "frame_path": "tmp/frame_49.jpg", "predictions": [], "persons": 0}, {"true_count": 250, "frame_count": 50, "frame_path": "tmp/frame_50.jpg", "predictions": [], "persons": 0}, {"true_count": 255, "frame_count": 51, "frame_path": "tmp/frame_51.jpg", "predictions": [], "persons": 0}, {"true_count": 260, "frame_count": 52, "frame_path": "tmp/frame_52.jpg", "predictions": [], "persons": 0}, {"true_count": 265, "frame_count": 53, "frame_path": "tmp/frame_53.jpg", "predictions": [], "persons": 0}, {"true_count": 270, "frame_count": 54, "frame_path": "tmp/frame_54.jpg", "predictions": [], "persons": 0}, {"true_count": 275, "frame_count": 55, "frame_path": "tmp/frame_55.jpg", "predictions": [], "persons": 0}, {"true_count": 280, "frame_count": 56, "frame_path": "tmp/frame_56.jpg", "predictions": [], "persons": 0}, {"true_count": 285, "frame_count": 57, "frame_path": "tmp/frame_57.jpg", "predictions": [], "persons": 0}, {"true_count": 290, "frame_count": 58, "frame_path": "tmp/frame_58.jpg", "predictions": [], "persons": 0}, {"true_count": 295, "frame_count": 59, "frame_path": "tmp/frame_59.jpg", "predictions": [], "persons": 0}, {"true_count": 300, "frame_count": 60, "frame_path": "tmp/frame_60.jpg", "predictions": [], "persons": 0}, {"true_count": 305, "frame_count": 61, "frame_path": "tmp/frame_61.jpg", "predictions": [], "persons": 0}, {"true_count": 310, "frame_count": 62, "frame_path": "tmp/frame_62.jpg", "predictions": [], "persons": 0}, {"true_count": 315, "frame_count": 63, "frame_path": "tmp/frame_63.jpg", "predictions": [], "persons": 0}, {"true_count": 320, "frame_count": 64, "frame_path": "tmp/frame_64.jpg", "predictions": [], "persons": 0}, {"true_count": 325, "frame_count": 65, "frame_path": "tmp/frame_65.jpg", "predictions": [], "persons": 0}, {"true_count": 330, "frame_count": 66, "frame_path": "tmp/frame_66.jpg", "predictions": [{"confidence": 0.5312909, "label": "person", "y_min": 260, "x_min": 241, "y_max": 300, "x_max": 299}], "persons": 1}, {"true_count": 335, "frame_count": 67, "frame_path": "tmp/frame_67.jpg", "predictions": [{"confidence": 0.53311086, "label": "person", "y_min": 261, "x_min": 308, "y_max": 300, "x_max": 366}, {"confidence": 0.588105, "label": "person", "y_min": 238, "x_min": 230, "y_max": 300, "x_max": 302}], "persons": 2}, {"true_count": 340, "frame_count": 68, "frame_path": "tmp/frame_68.jpg", "predictions": [{"confidence": 0.67819524, "label": "person", "y_min": 236, "x_min": 299, "y_max": 300, "x_max": 367}, {"confidence": 0.8037638, "label": "person", "y_min": 210, "x_min": 232, "y_max": 300, "x_max": 301}], "persons": 2}, {"true_count": 345, "frame_count": 69, "frame_path": "tmp/frame_69.jpg", "predictions": [{"confidence": 0.73915577, "label": "person", "y_min": 184, "x_min": 231, "y_max": 297, "x_max": 303}, {"confidence": 0.7822378, "label": "person", "y_min": 208, "x_min": 309, "y_max": 299, "x_max": 372}], "persons": 2}, {"true_count": 350, "frame_count": 70, "frame_path": "tmp/frame_70.jpg", "predictions": [{"confidence": 0.48572832, "label": "person", "y_min": 181, "x_min": 312, "y_max": 275, "x_max": 363}, {"confidence": 0.5224608, "label": "person", "y_min": 162, "x_min": 227, "y_max": 281, "x_max": 303}], "persons": 2}, {"true_count": 355, "frame_count": 71, "frame_path": "tmp/frame_71.jpg", "predictions": [], "persons": 0}, {"true_count": 360, "frame_count": 72, "frame_path": "tmp/frame_72.jpg", "predictions": [{"confidence": 0.5716876, "label": "horse", "y_min": 133, "x_min": 297, "y_max": 243, "x_max": 357}, {"confidence": 0.6193705, "label": "person", "y_min": 112, "x_min": 219, "y_max": 247, "x_max": 299}], "persons": 1}, {"true_count": 365, "frame_count": 73, "frame_path": "tmp/frame_73.jpg", "predictions": [{"confidence": 0.81277686, "label": "horse", "y_min": 107, "x_min": 296, "y_max": 204, "x_max": 357}], "persons": 0}, {"true_count": 370, "frame_count": 74, "frame_path": "tmp/frame_74.jpg", "predictions": [{"confidence": 0.75787085, "label": "horse", "y_min": 85, "x_min": 296, "y_max": 196, "x_max": 362}], "persons": 0}, {"true_count": 375, "frame_count": 75, "frame_path": "tmp/frame_75.jpg", "predictions": [{"confidence": 0.61125785, "label": "umbrella", "y_min": 59, "x_min": 298, "y_max": 172, "x_max": 370}], "persons": 0}, {"true_count": 380, "frame_count": 76, "frame_path": "tmp/frame_76.jpg", "predictions": [], "persons": 0}, {"true_count": 385, "frame_count": 77, "frame_path": "tmp/frame_77.jpg", "predictions": [], "persons": 0}, {"true_count": 390, "frame_count": 78, "frame_path": "tmp/frame_78.jpg", "predictions": [], "persons": 0}, {"true_count": 395, "frame_count": 79, "frame_path": "tmp/frame_79.jpg", "predictions": [{"confidence": 0.48277482, "label": "person", "y_min": 1, "x_min": 211, "y_max": 78, "x_max": 285}, {"confidence": 0.5762302, "label": "person", "y_min": 2, "x_min": 308, "y_max": 71, "x_max": 366}], "persons": 2}, {"true_count": 400, "frame_count": 80, "frame_path": "tmp/frame_80.jpg", "predictions": [], "persons": 0}, {"true_count": 405, "frame_count": 81, "frame_path": "tmp/frame_81.jpg", "predictions": [], "persons": 0}, {"true_count": 410, "frame_count": 82, "frame_path": "tmp/frame_82.jpg", "predictions": [], "persons": 0}, {"true_count": 415, "frame_count": 83, "frame_path": "tmp/frame_83.jpg", "predictions": [], "persons": 0}, {"true_count": 420, "frame_count": 84, "frame_path": "tmp/frame_84.jpg", "predictions": [], "persons": 0}, {"true_count": 425, "frame_count": 85, "frame_path": "tmp/frame_85.jpg", "predictions": [], "persons": 0}, {"true_count": 430, "frame_count": 86, "frame_path": "tmp/frame_86.jpg", "predictions": [{"confidence": 0.6691116, "label": "person", "y_min": 1, "x_min": 115, "y_max": 89, "x_max": 163}], "persons": 1}, {"true_count": 435, "frame_count": 87, "frame_path": "tmp/frame_87.jpg", "predictions": [], "persons": 0}, {"true_count": 440, "frame_count": 88, "frame_path": "tmp/frame_88.jpg", "predictions": [], "persons": 0}, {"true_count": 445, "frame_count": 89, "frame_path": "tmp/frame_89.jpg", "predictions": [], "persons": 0}, {"true_count": 450, "frame_count": 90, "frame_path": "tmp/frame_90.jpg", "predictions": [], "persons": 0}, {"true_count": 455, "frame_count": 91, "frame_path": "tmp/frame_91.jpg", "predictions": [{"confidence": 0.69577134, "label": "cat", "y_min": 52, "x_min": 109, "y_max": 153, "x_max": 184}], "persons": 0}, {"true_count": 460, "frame_count": 92, "frame_path": "tmp/frame_92.jpg", "predictions": [{"confidence": 0.8349685, "label": "person", "y_min": 74, "x_min": 112, "y_max": 194, "x_max": 186}], "persons": 1}, {"true_count": 465, "frame_count": 93, "frame_path": "tmp/frame_93.jpg", "predictions": [], "persons": 0}, {"true_count": 470, "frame_count": 94, "frame_path": "tmp/frame_94.jpg", "predictions": [{"confidence": 0.6335434, "label": "cat", "y_min": 111, "x_min": 124, "y_max": 209, "x_max": 199}], "persons": 0}, {"true_count": 475, "frame_count": 95, "frame_path": "tmp/frame_95.jpg", "predictions": [], "persons": 0}, {"true_count": 480, "frame_count": 96, "frame_path": "tmp/frame_96.jpg", "predictions": [], "persons": 0}, {"true_count": 485, "frame_count": 97, "frame_path": "tmp/frame_97.jpg", "predictions": [{"confidence": 0.6060986, "label": "cat", "y_min": 171, "x_min": 131, "y_max": 276, "x_max": 209}], "persons": 0}, {"true_count": 490, "frame_count": 98, "frame_path": "tmp/frame_98.jpg", "predictions": [{"confidence": 0.7160742, "label": "person", "y_min": 189, "x_min": 134, "y_max": 287, "x_max": 212}], "persons": 1}, {"true_count": 495, "frame_count": 99, "frame_path": "tmp/frame_99.jpg", "predictions": [{"confidence": 0.6101814, "label": "bird", "y_min": 211, "x_min": 140, "y_max": 298, "x_max": 217}], "persons": 0}, {"true_count": 500, "frame_count": 100, "frame_path": "tmp/frame_100.jpg", "predictions": [], "persons": 0}, {"true_count": 505, "frame_count": 101, "frame_path": "tmp/frame_101.jpg", "predictions": [], "persons": 0}, {"true_count": 510, "frame_count": 102, "frame_path": "tmp/frame_102.jpg", "predictions": [], "persons": 0}, {"true_count": 515, "frame_count": 103, "frame_path": "tmp/frame_103.jpg", "predictions": [], "persons": 0}, {"true_count": 520, "frame_count": 104, "frame_path": "tmp/frame_104.jpg", "predictions": [], "persons": 0}, {"true_count": 525, "frame_count": 105, "frame_path": "tmp/frame_105.jpg", "predictions": [], "persons": 0}, {"true_count": 530, "frame_count": 106, "frame_path": "tmp/frame_106.jpg", "predictions": [], "persons": 0}]